cte/__init__.py
cte/__main__.py
cte/cli_args.py
cte/config.py
cte/confluence.py
cte/excel.py
confluence_task_exporter-0.1.0.dist-info/LICENSE
confluence_task_exporter-0.1.0.dist-info/METADATA
confluence_task_exporter-0.1.0.dist-info/WHEEL
confluence_task_exporter-0.1.0.dist-info/entry_points.txt
confluence_task_exporter-0.1.0.dist-info/top_level.txt
confluence_task_exporter-0.1.0.dist-info/RECORD
