Metadata-Version: 2.1
Name: confluence-task-exporter
Version: 0.1.0
Summary: Library and cli app to export tasks from confluence pages and entire spaces
Author: Philipp Schmurr
Maintainer: Philipp Schmurr
Project-URL: Homepage, https://github.com/pypa/sampleproject
Project-URL: Bug Reports, https://github.com/pypa/sampleproject/issues
Project-URL: Funding, https://donate.pypi.org
Project-URL: Say Thanks!, http://saythanks.io/to/example
Project-URL: Source, https://github.com/pypa/sampleproject/
Keywords: confluence,tasks,exporter
Classifier: Development Status :: 3 - Alpha
Classifier: License :: OSI Approved :: MIT License
Classifier: Programming Language :: Python :: 3
Classifier: Programming Language :: Python :: 3.10
Classifier: Programming Language :: Python :: 3.11
Classifier: Programming Language :: Python :: 3.12
Classifier: Programming Language :: Python :: 3 :: Only
Requires-Python: >=3.8
License-File: LICENSE
Requires-Dist: beautifulsoup4 ~=4.12.3
Requires-Dist: lxml ~=5.3.0
Requires-Dist: pandas ~=2.2.3
Requires-Dist: xlsxwriter ~=3.2.0
